{
  "schema_name": "DoclingDocument",
  "version": "1.4.0",
  "name": "index",
  "origin": {
    "mimetype": "text/markdown",
    "binary_hash": 17782417911027697673,
    "filename": "index.md"
  },
  "furniture": {
    "self_ref": "#/furniture",
    "children": [],
    "content_layer": "furniture",
    "name": "_root_",
    "label": "unspecified"
  },
  "body": {
    "self_ref": "#/body",
    "children": [
      {
        "$ref": "#/texts/0"
      },
      {
        "$ref": "#/groups/0"
      },
      {
        "$ref": "#/texts/4"
      },
      {
        "$ref": "#/texts/5"
      },
      {
        "$ref": "#/texts/6"
      },
      {
        "$ref": "#/texts/7"
      },
      {
        "$ref": "#/groups/1"
      },
      {
        "$ref": "#/texts/11"
      }
    ],
    "content_layer": "body",
    "name": "_root_",
    "label": "unspecified"
  },
  "groups": [
    {
      "self_ref": "#/groups/0",
      "parent": {
        "$ref": "#/body"
      },
      "children": [
        {
          "$ref": "#/texts/1"
        },
        {
          "$ref": "#/texts/2"
        },
        {
          "$ref": "#/texts/3"
        }
      ],
      "content_layer": "body",
      "name": "list",
      "label": "list"
    },
    {
      "self_ref": "#/groups/1",
      "parent": {
        "$ref": "#/body"
      },
      "children": [
        {
          "$ref": "#/texts/8"
        },
        {
          "$ref": "#/texts/9"
        },
        {
          "$ref": "#/texts/10"
        }
      ],
      "content_layer": "body",
      "name": "list",
      "label": "list"
    }
  ],
  "texts": [
    {
      "self_ref": "#/texts/0",
      "parent": {
        "$ref": "#/body"
      },
      "children": [],
      "content_layer": "body",
      "label": "paragraph",
      "prov": [],
      "orig": "aliases:",
      "text": "aliases:"
    },
    {
      "self_ref": "#/texts/1",
      "parent": {
        "$ref": "#/groups/0"
      },
      "children": [],
      "content_layer": "body",
      "label": "list_item",
      "prov": [],
      "orig": "/2008/04/29/best-php-and-mysql-development-book/",
      "text": "/2008/04/29/best-php-and-mysql-development-book/",
      "enumerated": false,
      "marker": "-"
    },
    {
      "self_ref": "#/texts/2",
      "parent": {
        "$ref": "#/groups/0"
      },
      "children": [],
      "content_layer": "body",
      "label": "list_item",
      "prov": [],
      "orig": "database",
      "text": "database",
      "enumerated": false,
      "marker": "-"
    },
    {
      "self_ref": "#/texts/3",
      "parent": {
        "$ref": "#/groups/0"
      },
      "children": [],
      "content_layer": "body",
      "label": "list_item",
      "prov": [],
      "orig": "development",
      "text": "development",
      "enumerated": false,
      "marker": "-"
    },
    {
      "self_ref": "#/texts/4",
      "parent": {
        "$ref": "#/body"
      },
      "children": [],
      "content_layer": "body",
      "label": "paragraph",
      "prov": [],
      "orig": "I finally remembered this book when someone asked me about how to get started with PHP and MySQL development. If you get the chance, get a copy of this book:",
      "text": "I finally remembered this book when someone asked me about how to get started with PHP and MySQL development. If you get the chance, get a copy of this book:"
    },
    {
      "self_ref": "#/texts/5",
      "parent": {
        "$ref": "#/body"
      },
      "children": [],
      "content_layer": "body",
      "label": "paragraph",
      "prov": [],
      "orig": "PHP and MySQL Web Development   by Luke Welling, Laura Thomson",
      "text": "PHP and MySQL Web Development   by Luke Welling, Laura Thomson"
    },
    {
      "self_ref": "#/texts/6",
      "parent": {
        "$ref": "#/body"
      },
      "children": [],
      "content_layer": "body",
      "label": "paragraph",
      "prov": [],
      "orig": "Barnes & Noble:  http://snurl.com/265xp",
      "text": "Barnes & Noble:  http://snurl.com/265xp"
    },
    {
      "self_ref": "#/texts/7",
      "parent": {
        "$ref": "#/body"
      },
      "children": [],
      "content_layer": "body",
      "label": "paragraph",
      "prov": [],
      "orig": "Why do I like this book so much?",
      "text": "Why do I like this book so much?"
    },
    {
      "self_ref": "#/texts/8",
      "parent": {
        "$ref": "#/groups/1"
      },
      "children": [],
      "content_layer": "body",
      "label": "list_item",
      "prov": [],
      "orig": "[<RawText children='Teaching by application'>]",
      "text": "[<RawText children='Teaching by application'>]",
      "enumerated": false,
      "marker": "-"
    },
    {
      "self_ref": "#/texts/9",
      "parent": {
        "$ref": "#/groups/1"
      },
      "children": [],
      "content_layer": "body",
      "label": "list_item",
      "prov": [],
      "orig": "[<RawText children='Intertwined strategies'>]",
      "text": "[<RawText children='Intertwined strategies'>]",
      "enumerated": false,
      "marker": "-"
    },
    {
      "self_ref": "#/texts/10",
      "parent": {
        "$ref": "#/groups/1"
      },
      "children": [],
      "content_layer": "body",
      "label": "list_item",
      "prov": [],
      "orig": "[<RawText children='Lots of examples'>]",
      "text": "[<RawText children='Lots of examples'>]",
      "enumerated": false,
      "marker": "-"
    },
    {
      "self_ref": "#/texts/11",
      "parent": {
        "$ref": "#/body"
      },
      "children": [],
      "content_layer": "body",
      "label": "paragraph",
      "prov": [],
      "orig": "I'd be happy to loan my copy, but I've loaned it out and it never returned.",
      "text": "I'd be happy to loan my copy, but I've loaned it out and it never returned."
    }
  ],
  "pictures": [],
  "tables": [],
  "key_value_items": [],
  "form_items": [],
  "pages": {}
}