{
  "schema_name": "DoclingDocument",
  "version": "1.4.0",
  "name": "myfile",
  "origin": {
    "mimetype": "text/markdown",
    "binary_hash": 2422633229888281397,
    "filename": "myfile.md"
  },
  "furniture": {
    "self_ref": "#/furniture",
    "children": [],
    "content_layer": "furniture",
    "name": "_root_",
    "label": "unspecified"
  },
  "body": {
    "self_ref": "#/body",
    "children": [
      {
        "$ref": "#/texts/0"
      },
      {
        "$ref": "#/texts/1"
      },
      {
        "$ref": "#/texts/2"
      },
      {
        "$ref": "#/texts/3"
      },
      {
        "$ref": "#/texts/4"
      }
    ],
    "content_layer": "body",
    "name": "_root_",
    "label": "unspecified"
  },
  "groups": [],
  "texts": [
    {
      "self_ref": "#/texts/0",
      "parent": {
        "$ref": "#/body"
      },
      "children": [],
      "content_layer": "body",
      "label": "paragraph",
      "prov": [],
      "orig": "Installing new hardware may mean that new kernel need to be loaded when your server boots up. There's a two step process to making a new initrd file:",
      "text": "Installing new hardware may mean that new kernel need to be loaded when your server boots up. There's a two step process to making a new initrd file:"
    },
    {
      "self_ref": "#/texts/1",
      "parent": {
        "$ref": "#/body"
      },
      "children": [],
      "content_layer": "body",
      "label": "paragraph",
      "prov": [],
      "orig": "First,  add the appropriate line to your /etc/modules.conf or /etc/modprobe.conf which corresponds to your new kernel module.",
      "text": "First,  add the appropriate line to your /etc/modules.conf or /etc/modprobe.conf which corresponds to your new kernel module."
    },
    {
      "self_ref": "#/texts/2",
      "parent": {
        "$ref": "#/body"
      },
      "children": [],
      "content_layer": "body",
      "label": "paragraph",
      "prov": [],
      "orig": "Next,  rebuild the initial ram disk after making a backup of the current one:",
      "text": "Next,  rebuild the initial ram disk after making a backup of the current one:"
    },
    {
      "self_ref": "#/texts/3",
      "parent": {
        "$ref": "#/body"
      },
      "children": [],
      "content_layer": "body",
      "label": "code",
      "prov": [],
      "orig": "# cp /boot/initrd-`uname -r`.img /boot/initrd-`uname -r`.img.bak\n# mkinitrd -f initrd-`uname -r`.img `uname -r`",
      "text": "# cp /boot/initrd-`uname -r`.img /boot/initrd-`uname -r`.img.bak\n# mkinitrd -f initrd-`uname -r`.img `uname -r`",
      "captions": [],
      "references": [],
      "footnotes": [],
      "code_language": "unknown"
    },
    {
      "self_ref": "#/texts/4",
      "parent": {
        "$ref": "#/body"
      },
      "children": [],
      "content_layer": "body",
      "label": "paragraph",
      "prov": [],
      "orig": "Reboot the server now and make sure the new driver is loaded properly.",
      "text": "Reboot the server now and make sure the new driver is loaded properly."
    }
  ],
  "pictures": [],
  "tables": [],
  "key_value_items": [],
  "form_items": [],
  "pages": {}
}