{
  "schema_name": "DoclingDocument",
  "version": "1.4.0",
  "name": "index",
  "origin": {
    "mimetype": "text/markdown",
    "binary_hash": 8778579768362894123,
    "filename": "index.md"
  },
  "furniture": {
    "self_ref": "#/furniture",
    "children": [],
    "content_layer": "furniture",
    "name": "_root_",
    "label": "unspecified"
  },
  "body": {
    "self_ref": "#/body",
    "children": [
      {
        "$ref": "#/texts/0"
      },
      {
        "$ref": "#/groups/0"
      },
      {
        "$ref": "#/texts/6"
      },
      {
        "$ref": "#/texts/7"
      },
      {
        "$ref": "#/groups/1"
      },
      {
        "$ref": "#/texts/12"
      },
      {
        "$ref": "#/texts/13"
      },
      {
        "$ref": "#/texts/14"
      },
      {
        "$ref": "#/texts/15"
      }
    ],
    "content_layer": "body",
    "name": "_root_",
    "label": "unspecified"
  },
  "groups": [
    {
      "self_ref": "#/groups/0",
      "parent": {
        "$ref": "#/body"
      },
      "children": [
        {
          "$ref": "#/texts/1"
        },
        {
          "$ref": "#/texts/2"
        },
        {
          "$ref": "#/texts/3"
        },
        {
          "$ref": "#/texts/4"
        },
        {
          "$ref": "#/texts/5"
        }
      ],
      "content_layer": "body",
      "name": "list",
      "label": "list"
    },
    {
      "self_ref": "#/groups/1",
      "parent": {
        "$ref": "#/body"
      },
      "children": [
        {
          "$ref": "#/texts/8"
        },
        {
          "$ref": "#/texts/9"
        },
        {
          "$ref": "#/texts/10"
        },
        {
          "$ref": "#/texts/11"
        }
      ],
      "content_layer": "body",
      "name": "list",
      "label": "list"
    }
  ],
  "texts": [
    {
      "self_ref": "#/texts/0",
      "parent": {
        "$ref": "#/body"
      },
      "children": [],
      "content_layer": "body",
      "label": "paragraph",
      "prov": [],
      "orig": "aliases:",
      "text": "aliases:"
    },
    {
      "self_ref": "#/texts/1",
      "parent": {
        "$ref": "#/groups/0"
      },
      "children": [],
      "content_layer": "body",
      "label": "list_item",
      "prov": [],
      "orig": "/2013/11/17/information-security-nuggets-from-devops-weekly-150/",
      "text": "/2013/11/17/information-security-nuggets-from-devops-weekly-150/",
      "enumerated": false,
      "marker": "-"
    },
    {
      "self_ref": "#/texts/2",
      "parent": {
        "$ref": "#/groups/0"
      },
      "children": [],
      "content_layer": "body",
      "label": "list_item",
      "prov": [],
      "orig": "devops",
      "text": "devops",
      "enumerated": false,
      "marker": "-"
    },
    {
      "self_ref": "#/texts/3",
      "parent": {
        "$ref": "#/groups/0"
      },
      "children": [],
      "content_layer": "body",
      "label": "list_item",
      "prov": [],
      "orig": "advice",
      "text": "advice",
      "enumerated": false,
      "marker": "-"
    },
    {
      "self_ref": "#/texts/4",
      "parent": {
        "$ref": "#/groups/0"
      },
      "children": [],
      "content_layer": "body",
      "label": "list_item",
      "prov": [],
      "orig": "networking",
      "text": "networking",
      "enumerated": false,
      "marker": "-"
    },
    {
      "self_ref": "#/texts/5",
      "parent": {
        "$ref": "#/groups/0"
      },
      "children": [],
      "content_layer": "body",
      "label": "list_item",
      "prov": [],
      "orig": "security",
      "text": "security",
      "enumerated": false,
      "marker": "-"
    },
    {
      "self_ref": "#/texts/6",
      "parent": {
        "$ref": "#/body"
      },
      "children": [],
      "content_layer": "body",
      "label": "paragraph",
      "prov": [],
      "orig": "Keeping an eye out for the  DevOps Weekly email  is something I've enjoyed since it started at the end of 2010. It's usually chock full of tips for systems engineers, developers, managers, or anyone who is focused on environments that utilize continuous integration and deployment strategies. Quite a few of the tips are totally relevant for information security professionals who are looking for an edge at work.",
      "text": "Keeping an eye out for the  DevOps Weekly email  is something I've enjoyed since it started at the end of 2010. It's usually chock full of tips for systems engineers, developers, managers, or anyone who is focused on environments that utilize continuous integration and deployment strategies. Quite a few of the tips are totally relevant for information security professionals who are looking for an edge at work."
    },
    {
      "self_ref": "#/texts/7",
      "parent": {
        "$ref": "#/body"
      },
      "children": [],
      "content_layer": "body",
      "label": "paragraph",
      "prov": [],
      "orig": "This week, there are four links worth reviewing if you work in information security:",
      "text": "This week, there are four links worth reviewing if you work in information security:"
    },
    {
      "self_ref": "#/texts/8",
      "parent": {
        "$ref": "#/groups/1"
      },
      "children": [],
      "content_layer": "body",
      "label": "list_item",
      "prov": [],
      "orig": "[<RawText children='sitespeed.io'>]",
      "text": "[<RawText children='sitespeed.io'>]",
      "enumerated": false,
      "marker": "-"
    },
    {
      "self_ref": "#/texts/9",
      "parent": {
        "$ref": "#/groups/1"
      },
      "children": [],
      "content_layer": "body",
      "label": "list_item",
      "prov": [],
      "orig": "[<RawText children='Burnout, Recovery and Honesty'>]",
      "text": "[<RawText children='Burnout, Recovery and Honesty'>]",
      "enumerated": false,
      "marker": "-"
    },
    {
      "self_ref": "#/texts/10",
      "parent": {
        "$ref": "#/groups/1"
      },
      "children": [],
      "content_layer": "body",
      "label": "list_item",
      "prov": [],
      "orig": "[<RawText children='Audits of High Deployment Environments'>]",
      "text": "[<RawText children='Audits of High Deployment Environments'>]",
      "enumerated": false,
      "marker": "-"
    },
    {
      "self_ref": "#/texts/11",
      "parent": {
        "$ref": "#/groups/1"
      },
      "children": [],
      "content_layer": "body",
      "label": "list_item",
      "prov": [],
      "orig": "[<RawText children='A tcpdump Primer'>]",
      "text": "[<RawText children='A tcpdump Primer'>]",
      "enumerated": false,
      "marker": "-"
    },
    {
      "self_ref": "#/texts/12",
      "parent": {
        "$ref": "#/body"
      },
      "children": [],
      "content_layer": "body",
      "label": "paragraph",
      "prov": [],
      "orig": "The idea behind  sitespeed.io  is to monitor an application's performance through deployments. Availability is critical to security (although it's often de-prioritized until you feel the pain) and it can signal an attack in process. Performance degradation over time could allow the application to be knocked offline from smaller attacks.",
      "text": "The idea behind  sitespeed.io  is to monitor an application's performance through deployments. Availability is critical to security (although it's often de-prioritized until you feel the pain) and it can signal an attack in process. Performance degradation over time could allow the application to be knocked offline from smaller attacks."
    },
    {
      "self_ref": "#/texts/13",
      "parent": {
        "$ref": "#/body"
      },
      "children": [],
      "content_layer": "body",
      "label": "paragraph",
      "prov": [],
      "orig": "Burnout, Recovery and Honesty  is an anecdote from an IT worker about how their job changed their personal and home life. It's worth a read so that you can catch the warning signs of burnout within yourself and your coworkers.",
      "text": "Burnout, Recovery and Honesty  is an anecdote from an IT worker about how their job changed their personal and home life. It's worth a read so that you can catch the warning signs of burnout within yourself and your coworkers."
    },
    {
      "self_ref": "#/texts/14",
      "parent": {
        "$ref": "#/body"
      },
      "children": [],
      "content_layer": "body",
      "label": "paragraph",
      "prov": [],
      "orig": "Bringing continuous deployments to large companies is challenging due to the number of compliance and regulatory programs. A great slide deck called  Audits of High Deployment Environments  covers some of the basic strategies for how to deal with these challenges.",
      "text": "Bringing continuous deployments to large companies is challenging due to the number of compliance and regulatory programs. A great slide deck called  Audits of High Deployment Environments  covers some of the basic strategies for how to deal with these challenges."
    },
    {
      "self_ref": "#/texts/15",
      "parent": {
        "$ref": "#/body"
      },
      "children": [],
      "content_layer": "body",
      "label": "paragraph",
      "prov": [],
      "orig": "Finally, my favorite nugget from this week's newsletter is the the  tcpdump primer . It's a great resource for people who have never used tcpdump or for those of us who have only used some of the basic functionality. You'll be able to get more data out of tcpdump with less fuss after reading the post.",
      "text": "Finally, my favorite nugget from this week's newsletter is the the  tcpdump primer . It's a great resource for people who have never used tcpdump or for those of us who have only used some of the basic functionality. You'll be able to get more data out of tcpdump with less fuss after reading the post."
    }
  ],
  "pictures": [],
  "tables": [],
  "key_value_items": [],
  "form_items": [],
  "pages": {}
}