{
  "schema_name": "DoclingDocument",
  "version": "1.4.0",
  "name": "index",
  "origin": {
    "mimetype": "text/markdown",
    "binary_hash": 1912660993441392992,
    "filename": "index.md"
  },
  "furniture": {
    "self_ref": "#/furniture",
    "children": [],
    "content_layer": "furniture",
    "name": "_root_",
    "label": "unspecified"
  },
  "body": {
    "self_ref": "#/body",
    "children": [
      {
        "$ref": "#/texts/0"
      },
      {
        "$ref": "#/groups/0"
      },
      {
        "$ref": "#/texts/3"
      },
      {
        "$ref": "#/texts/4"
      }
    ],
    "content_layer": "body",
    "name": "_root_",
    "label": "unspecified"
  },
  "groups": [
    {
      "self_ref": "#/groups/0",
      "parent": {
        "$ref": "#/body"
      },
      "children": [
        {
          "$ref": "#/texts/1"
        },
        {
          "$ref": "#/texts/2"
        }
      ],
      "content_layer": "body",
      "name": "list",
      "label": "list"
    }
  ],
  "texts": [
    {
      "self_ref": "#/texts/0",
      "parent": {
        "$ref": "#/body"
      },
      "children": [],
      "content_layer": "body",
      "label": "paragraph",
      "prov": [],
      "orig": "aliases:",
      "text": "aliases:"
    },
    {
      "self_ref": "#/texts/1",
      "parent": {
        "$ref": "#/groups/0"
      },
      "children": [],
      "content_layer": "body",
      "label": "list_item",
      "prov": [],
      "orig": "/2007/01/29/make-apache-logs-mimic-iis/",
      "text": "/2007/01/29/make-apache-logs-mimic-iis/",
      "enumerated": false,
      "marker": "-"
    },
    {
      "self_ref": "#/texts/2",
      "parent": {
        "$ref": "#/groups/0"
      },
      "children": [],
      "content_layer": "body",
      "label": "list_item",
      "prov": [],
      "orig": "web",
      "text": "web",
      "enumerated": false,
      "marker": "-"
    },
    {
      "self_ref": "#/texts/3",
      "parent": {
        "$ref": "#/body"
      },
      "children": [],
      "content_layer": "body",
      "label": "paragraph",
      "prov": [],
      "orig": "To make Apache write logs similar to IIS, toss this into your Apache configuration:",
      "text": "To make Apache write logs similar to IIS, toss this into your Apache configuration:"
    },
    {
      "self_ref": "#/texts/4",
      "parent": {
        "$ref": "#/body"
      },
      "children": [],
      "content_layer": "body",
      "label": "code",
      "prov": [],
      "orig": "LogFormat \"%{%Y-%m-%d %H:%M:%S}t %h %u %m %U %q %>s %b %T %H %{Host}i %{User-Agent}i %{Cookie}i %{Referer}i\" iis",
      "text": "LogFormat \"%{%Y-%m-%d %H:%M:%S}t %h %u %m %U %q %>s %b %T %H %{Host}i %{User-Agent}i %{Cookie}i %{Referer}i\" iis",
      "captions": [],
      "references": [],
      "footnotes": [],
      "code_language": "unknown"
    }
  ],
  "pictures": [],
  "tables": [],
  "key_value_items": [],
  "form_items": [],
  "pages": {}
}